MANIFEST.in
setup.py
anthill/event/__init__.py
anthill/event/admin.py
anthill/event/handler.py
anthill/event/options.py
anthill/event/server.py
anthill/event/model/__init__.py
anthill/event/model/event.py
anthill/event/sql/category_scheme.sql
anthill/event/sql/common_scheme.sql
anthill/event/sql/event_group_participants.sql
anthill/event/sql/event_participants.sql
anthill/event/sql/events.sql
anthill_event.egg-info/PKG-INFO
anthill_event.egg-info/SOURCES.txt
anthill_event.egg-info/dependency_links.txt
anthill_event.egg-info/namespace_packages.txt
anthill_event.egg-info/not-zip-safe
anthill_event.egg-info/requires.txt
anthill_event.egg-info/top_level.txt