Metadata-Version: 1.0
Name: anthill-event
Version: 0.2
Summary: Time-Limited events service for Anthill platform
Home-page: https://github.com/anthill-platform/anthill-event
Author: desertkun
Author-email: desertkun@gmail.com
License: MIT
Platform: UNKNOWN
